LICENSE
MANIFEST.in
README.md
requirements.txt
requirements_db.txt
requirements_geo.txt
requirements_xls.txt
setup.cfg
setup.py
test_requirements.txt
tox.ini
landgrab/__init__.py
landgrab/__main__.py
landgrab/config.py
landgrab/engine.py
landgrab/env.py
landgrab/transform.py
landgrab.egg-info/PKG-INFO
landgrab.egg-info/SOURCES.txt
landgrab.egg-info/dependency_links.txt
landgrab.egg-info/entry_points.txt
landgrab.egg-info/not-zip-safe
landgrab.egg-info/requires.txt
landgrab.egg-info/top_level.txt
landgrab/contrib/__init__.py
landgrab/contrib/db/__init__.py
landgrab/contrib/db/sources.py
landgrab/contrib/geo/__init__.py
landgrab/contrib/geo/formats.py
landgrab/contrib/geo/tasks.py
landgrab/contrib/xls/__init__.py
landgrab/contrib/xls/formats.py
landgrab/format/__init__.py
landgrab/format/jsonlines.py
landgrab/format/raw.py
landgrab/format/rows.py
landgrab/sink/__init__.py
landgrab/sink/file.py
landgrab/sink/s3.py
landgrab/source/__init__.py
landgrab/source/file.py
landgrab/source/http.py
landgrab/source/s3.py
landgrab/task/__init__.py
landgrab/task/dict.py
tests/test.py
tests/__pycache__/test_FIXME.cpython-27-PYTEST.pyc