Metadata-Version: 2.1
Name: landgrab
Version: 0.2.0
Summary: Geospatial data hoarding system
Home-page: https://github.com/StationA/landgrab
Author: Station A
Author-email: software@stationa.com
License: License :: OSI Approved :: MIT License
Platform: UNKNOWN
Provides-Extra: geo
Provides-Extra: db
Provides-Extra: xls
